{
    "friends and groups": null,
    "thanks!": null,
    "show": null,
    "description": null,
    "your email wasn't verified": null,
    "me": null,
    "refuse": null,
    "friends list": "venneliste",
    "previous searches": null,
    "find friends": "find venner",
    "owner": null,
    "edit your settings": null,
    "destroy group": null,
    "requests you sent": null,
    "our beloved translators": null,
    "next action": null,
    "this email is unknown": null,
    "create group": null,
    "go to group's inventory": null,
    "that's already your username": null,
    "change password": null,
    "ongoing": null,
    "Request Entity Too Large": null,
    "search a group": null,
    "position": null,
    "credits": null,
    "step 1: Choose a username": null,
    "set your position": null,
    "Look who was already there! Friend request sent": null,
    "global": null,
    "keep an inventory of your books": "Foretag en oversigt over dine bøger",
    "exchanges": null,
    "That's also the place where you can create groups.": null,
    "photo credits:": null,
    "last added": null,
    "groups you just visited that the user is part of:": null,
    "enter a group description": null,
    "ambassador": null,
    "invalid ISBN": null,
    "Group name:": null,
    "see more": null,
    "isbn": "isbn",
    "groups name can't be longer than 60 characters": null,
    "comment can't be longer than 5000 characters": null,
    "oops": null,
    "browse books": null,
    "edit data": "rediger data",
    "back to welcome screen": "tilbage til velkomstskærmen",
    "archived": null,
    "send friend request": null,
    "discussions": null,
    "change picture": "ændre billede",
    "your friends": null,
    "books nearby": null,
    "source": null,
    "credit/debit card": null,
    "emails": null,
    "accept": null,
    "back to your inventory": "tilbage til din beholdning",
    "add private notes": null,
    "no suggestions available": null,
    "this email is already used": null,
    "not available yet": null,
    "you aren't connected to anyone yet": null,
    "inventorying": null,
    "activity": null,
    "browse": null,
    "find friends to share your inventory with!": null,
    "sign out": "log ud",
    "following activity": null,
    "code": null,
    "see the API documentation": null,
    "edit": "rediger",
    "select": null,
    "the bio can't be longer than 1000 characters": null,
    "back": "tilbage",
    "see on Wikipedia": "se på Wikipedia",
    "more": null,
    "author": null,
    "add it to my inventory": "tilføj det til min beholdning",
    "commons": null,
    "you need to be connected to send a friend request": null,
    "group description can't be longer than 5000 characters": null,
    "email me when": null,
    "add a personalized message": null,
    "you requested to join is waiting for approval": null,
    "validate user's request to join the group": null,
    "udpate password": null,
    "member": null,
    "distance:": null,
    "Welcome": null,
    "Europe": null,
    "request to join group": null,
    "feedback & news": "tilbagemeldinger og nyheder",
    "private": "privat",
    "user search": null,
    "select a picture": null,
    "created:": "oprettet:",
    "invalid description": null,
    "social networks": "sociale netværk",
    "download ebook": null,
    "edit the group's position": null,
    "you have a position set": null,
    "classic": null,
    "group members": null,
    "publisher": null,
    "a popup should now open to let you verify your credentials": null,
    "send": null,
    "added": null,
    "the group has a position set": null,
    "friend": null,
    "geolocation": null,
    "from": null,
    "clear history": null,
    "something went wrong :(": null,
    "this username isn't available": null,
    "login": "log på",
    "customize the number of days between activity summary emails": null,
    "in my friends' items": "i mine venners poster",
    "that would really help us if you could say a few words about why you're leaving:": null,
    "invalid url": null,
    "cancel request": null,
    "remove from group": null,
    "scan a barcode": "scan en stregkode",
    "edit notes": null,
    "only available from mobiles for now": "kun tilgængelig til smartphones for nu",
    "my inventory": null,
    "beautiful Creative Commons pictures by:": null,
    "help other users to understand what this group is about": null,
    "your position isn't set yet": null,
    "project": null,
    "danger zone": null,
    "edit your position": null,
    "username can't contain space": null,
    "comment": "kommentar",
    "no item found": null,
    "username can only contain letters, figures or _": null,
    "let's just create the book card": null,
    "add or search a book": "Tilføj eller søg efter en bog",
    "archive": null,
    "send invitations": null,
    "send an email to reset my password": null,
    "who would you like to share books with?": null,
    "hide": null,
    "pending friends requests": null,
    "your message": null,
    "or": "eller:",
    "you?": null,
    "see profile": null,
    "find friends by username from here": null,
    "group name can't be longer than 60 characters": null,
    "contributors": null,
    "search for users": null,
    "choose a transaction mode": null,
    "validate and add another book": null,
    "share": null,
    "from a file": null,
    "in my inventory": "i min beholdning",
    "sign up": "tilmeld",
    "you aren't in any group yet": null,
    "create a password": null,
    "matching books in your network": null,
    "no other category for now": "ingen anden kategori for nu",
    "Search from here by title, author or book id (ISBN)": null,
    "other operations:": "andre handlinger:",
    "as you are not a member of the group, you can only see members' public books": null,
    "Who can see it?": "Hvem kan se det?",
    "this action can't be undone": "denne handling kan ikke fortrydes",
    "can't reach the server": null,
    "enter an image url": null,
    "cancel": "annuller",
    "public": "offentlig",
    "discard user's request to join the group": null,
    "donate": null,
    "create an account": null,
    "not found": null,
    "title": "titel",
    "invalid email": null,
    "couldn't obtain your position": null,
    "share it with others": "del det med andre",
    "requests": null,
    "Welcome on Inventaire": null,
    "via the API": null,
    "members": null,
    "others": "andre",
    "welcome in your inventory!": null,
    "search": "søg",
    "no request": "ingen anmodninger",
    "search a book by title, author or ISBN": null,
    "appear in search results": null,
    "save changes": null,
    "the group's position isn't set yet": null,
    "couldn't parse emails": null,
    "epub": null,
    "username": "brugernavn",
    "your friends and communities are the best library": null,
    "edit profile": "rediger profil",
    "needed": "har brug for",
    "loading": null,
    "password should be 8 characters minimum": null,
    "download epub": null,
    "add a book to your inventory": null,
    "new password": null,
    "sent": null,
    "only possible from your smartphone' browser for now.": null,
    "unselect": null,
    "couldn't find your book?": "kunne ikke finde din bog?",
    "P1476": null,
    "no more pending requests": null,
    "validate": "bekræft",
    "invite friends": null,
    "already up-to-date": null,
    "current password": null,
    "you have no more pending invitations": null,
    "back to search results": null,
    "alternative": null,
    "Ctrl+Enter to send": null,
    "in my items": "i mine poster",
    "from a URL": null,
    "download": null,
    "books": "bøger",
    "you can't leave the group without naming another admin": null,
    "profile pic": "profilbillede",
    "I'm looking for it": "Jeg leder efter det",
    "articles": null,
    "create a group": null,
    "edit group name": null,
    "available for": "tilgængelig for",
    "this book I can lend, this book I can give, this one is for sell...": null,
    "username or password is invalid": null,
    "selling": "sælger",
    "You own your data": "Din egen data",
    "this book isn't in the database: let's just create the book card": null,
    "Step 2: associate your account with an email": null,
    "login with Persona": null,
    "Empowering the Transition": "Styrker Omstillingen",
    "our mission & values": null,
    "did you mean:": null,
    "transaction": null,
    "no pending requests": null,
    "subscribe": null,
    "edited": null,
    "username should be 2 characters minimum": null,
    "the library of your friends and communities": null,
    "how to contribute": null,
    "search for your friends": null,
    "I can lend it": "jeg kan udleje den/det",
    "forgot your password?": null,
    "a few words on you?": null,
    "you haven't added any friend yet": null,
    "friends & groups": null,
    "read online": null,
    "Built on and for Open Knowledge": "Byg videre på og for Open Knowdledge",
    "choose who can see that you have this book": null,
    "wrong password": null,
    "article": null,
    "emails separated by a comma": null,
    "settings": "indstillinger",
    "I'm selling it": null,
    "groups": null,
    "ex: Hamlet": "fx: Hamlet",
    "groups in common:": null,
    "email will not be publicly displayed.": null,
    "add a picture": "tilføj et billede",
    "this username is already used": null,
    "group name:": null,
    "make a one-time or recurrent donation": null,
    "update bio": null,
    "unselect all": null,
    "giving": "give",
    "Search": "Søg",
    "this resource doesn't exist or you don't have the right to access it": null,
    "edit group cover": null,
    "add to my inventory": "tilføj til min beholdning",
    "created": null,
    "Books:": null,
    "select all": null,
    "forgot password?": null,
    "or login with": null,
    "books in your network": null,
    "cancel deletion": null,
    "Something went wrong :(": null,
    "invite friends by email": null,
    "can't find any user at this location": null,
    "delete position": null,
    "go to the group inventory": null,
    "Built on and in Open Source": "Byg videre på og i Open Source",
    "sign up with Persona": null,
    "you're all set to start exploring!": null,
    "subject": null,
    "requests waiting your approval": null,
    "invalid username": null,
    "waiting for your answer": null,
    "your friends are your best library": null,
    "only you can see it": null,
    "feedback": null,
    "close": null,
    "search a book": null,
    "search results": "søge resultater",
    "by email address": null,
    "edit comment": null,
    "P364": null,
    "save": null,
    "post comment": null,
    "it doesn't look like an email": null,
    "discard friend request": null,
    "send feedback": null,
    "I have it and it's available for:": "Jeg har det og det er tilgængeligt for:",
    "group": null,
    "nearby": null,
    "username or password is incorrect": null,
    "stop following": null,
    "cover": "omslag",
    "wrong user": null,
    "who else has it?": null,
    "transactions": null,
    "cancel friend request": null,
    "add": null,
    "no friends to invite": null,
    "requests waiting for your answer": null,
    "delete your account": null,
    "import a picture": null,
    "decline": null,
    "full-time team": null,
    "search/add a book": null,
    "book": null,
    "send request": null,
    "select your position": null,
    "A book you want to share? Add it to your inventory!": null,
    "some of the last books published": "nogle af de tidligere udgivede bøger",
    "delete": null,
    "development": "udvikling",
    "this is visible by anyone who can see this item": null,
    "invite": null,
    "language": "sprog",
    "public books": null,
    "only me": "kun mig",
    "leave group": null,
    "friends": "venner",
    "actions": null,
    "add a book": null,
    "non-monetary donations": null,
    "personalized message": null,
    "no item here": "ingen poster her",
    "username should be 20 characters maximum": null,
    "design": null,
    "ebooks on gutenberg.org": null,
    "labs": "laboratorier",
    "no group found with this name": null,
    "see all": null,
    "users": null,
    "accept invitation": null,
    "add friend": null,
    "make the inventory of your books and mutualize with your friends and communities into an infinite library!": null,
    "The books you lend might actually come back now!": null,
    "invitations": null,
    "are you sure?": "er du sikker?",
    "you need to be connected to comment": null,
    "external scanner": null,
    "create": null,
    "network": null,
    "select the group's position": null,
    "yes": "ja",
    "name": null,
    "the server doesn't answer as expected.": null,
    "Search your friends in the current users or invite them to join!": null,
    "waiting for geolocation": null,
    "invited": null,
    "your friends and communities are your best library": null,
    "go get it!": null,
    "contribute": null,
    "set the group's position": null,
    "cookies are disabled": null,
    "contact email": "kontakt e-mail",
    "selected": null,
    "books:": null,
    "unavailable": null,
    "upload your collection from another website": null,
    "details": null,
    "send email": null,
    "and of what can be done with them:": null,
    "who has it?": "hvem har det?",
    "ex: William Shakespeare": "fx: William Shakespeare",
    "retry": null,
    "no": "nej",
    "or just scan your books' barcode": null,
    "url": null,
    "share it with your friends and communities": "del det med dine venner og dine fællesskaber",
    "advice:": null,
    "Remember the books you lend or borrow": null,
    "no notification": "ingen notifikationer",
    "get a tour": null,
    "email": null,
    "I need help on switching from Persona to an account with a password": null,
    "learn more": null,
    "user": null,
    "request waiting for your answer": null,
    "ex: 9782070368228": "fx: 9782070368228",
    "from:": null,
    "unauthorized api access": null,
    "scan": null,
    "Always dreamed of a collaborative library for your coworking / association / book club? Here it is!": null,
    "filter group members": null,
    "personal notes": "personlig noter",
    "translation": null,
    "edit data on Wikidata": null,
    "notifications": "notifikationer",
    "admin": null,
    "save position": null,
    "more details": "flere detaljer",
    "persona": null,
    "edit notifications": null,
    "researched books": "forskede bøger",
    "experimentations": "eksperimentering",
    "ex: the secret club of Proustian experts": null,
    "forgot password": null,
    "you need to be connected to add a book to your inventory": null,
    "can't find any group at this location": null,
    "post message": null,
    "reset password": null,
    "search your friends in the current users or invite them to join!": null,
    "ask for help": null,
    "import": null,
    "I'm giving it": "Jeg giver den/det",
    "email or password is incorrect": null,
    "I have it and it is available for:": "Jeg har det og det er tilgængeligt for:",
    "you can now find books people nearby have to give, share or sell!": null,
    "otherwise, let's just create the book card": null,
    "members:": null,
    "private notes": null,
    "data": null,
    "only those who get the link or are invited can find this group": null,
    "password": null,
    "missing image": null,
    "profile": null,
    "group name": null,
    "otherwise": null,
    "received": null,
    "authors": null,
    "emails separated by a coma": null,
    "you need to be connected to edit this page": null,
    "public items": "offentlige poster",
    "request you sent": null,
    "distance from you": null,
    "refresh data": null,
    "make admin": null,
    "change visibility:": "ændre synlighed",
    "news": "nyheder",
    "friends requests": "venneanmodninger",
    "edit group description": null,
    "your groups": null,
    "your friends' and groups' books": null,
    "our love wasn't possible because": null,
    "requested": null,
    "accept friend request": null,
    "can't find anyone with that name": null,
    "change email": null,
    "or email address": null,
    "editions": "udgave",
    "pending": null,
    "go to your inventory to see the imported books": null,
    "login to your inventory": null,
    "to:": null,
    "that's you": null,
    "shared with friends": "delt med venner",
    "unfriend": "fjern ven",
    "Just Books. For now.": "Kun bøger. For nu.",
    "invalid position: ": null,
    "pages": null,
    "that's already your email": null,
    "awesome people helping designing the project's future": null,
    "change username": "ændre brugernavn",
    "confirm": null,
    "data exports": "eksporterede data",
    "this group appears in search results": null,
    "can't find any group member with that name": null,
    "groups in common": null,
    "switch to another language or change your profile picture from there": null,
    "an author is required": null,
    "lending": "udlåne",
    "totally randomly-selected messages from the people of the Internet": null,
    "Home": "Hjem",
    "ex: 978-2-07-036822-8": null
}