{
    "a few words on you?": null,
    "accept": "accetta",
    "accept friend request": null,
    "accept invitation": null,
    "actions": null,
    "activity": "attività",
    "add": null,
    "add a book": null,
    "add a book to the database": null,
    "add a book to your inventory": null,
    "add a personalized message": null,
    "add a picture": "aggiungi un'immagine",
    "add a serie from this author": null,
    "add a work from this author": null,
    "add a work to this serie": null,
    "Add an edition by its ISBN": null,
    "add an edition without an ISBN": null,
    "add friend": null,
    "add more details": null,
    "add to my inventory": "aggiungi al mio inventario",
    "added": null,
    "admin": null,
    "admin section": null,
    "advice:": null,
    "all": null,
    "all languages": null,
    "Always dreamed of a collaborative library for your coworking / association / book club? Here it is!": null,
    "ambassador": null,
    "and of what can be done with them:": null,
    "appear in search results": null,
    "archive": null,
    "archived": null,
    "Are you sure you want to delete this statement?": null,
    "article": null,
    "articles": null,
    "as you are not a member of the group, you can only see members' public books": null,
    "ask us anything": null,
    "author": "autore",
    "authors": "autori",
    "available for": "disponibile per",
    "back": "indietro",
    "back to welcome screen": "ritorna alla pagina di benvenuto",
    "back to your inventory": "fai il backup del tuo inventario",
    "beautiful Creative Commons pictures by:": null,
    "book": "libro",
    "book series": null,
    "books": "libri",
    "books nearby": null,
    "books:": "libri",
    "browse": null,
    "browse books": null,
    "Built on and for Open Knowledge": null,
    "Built on and in Open Source": null,
    "by email address": null,
    "can you tell us more about this work and this particular edition?": null,
    "can't find any group at this location": null,
    "can't find any group member with that name": null,
    "can't find any user at this location": null,
    "can't find anyone with that name": null,
    "can't reach the server": null,
    "cancel": "cancella",
    "cancel friend request": null,
    "cancel request": null,
    "change email": null,
    "change password": null,
    "change picture": "cambia immagine",
    "change username": null,
    "change visibility:": "cambia visibilità:",
    "chat": null,
    "clear history": null,
    "close": null,
    "code": null,
    "comic book series": null,
    "comment": "commento",
    "comment can't be longer than 5000 characters": null,
    "commons": null,
    "confirm": "conferma",
    "Connect Wikidata account": null,
    "contribute": null,
    "contributions": null,
    "contributors": null,
    "cookies are disabled": null,
    "couldn't find your book?": null,
    "couldn't parse emails": null,
    "cover": "copertina",
    "create": null,
    "create a group": "crea un gruppo",
    "create a password": null,
    "create an account": "crea un account",
    "create and add to your inventory": null,
    "create and go to the book's page": null,
    "create and go to the edition's page": null,
    "create and go to the series' page": null,
    "create and return to the work's page": null,
    "create group": null,
    "created": null,
    "created:": "creato:",
    "credit/debit card": null,
    "credits": null,
    "Ctrl+Enter to send": "Ctrl+Invio per inviare",
    "current password": null,
    "danger zone": null,
    "data": null,
    "data exports": "esportazione dati",
    "day": "giorno",
    "decline": "rifiuta",
    "delete": "elimina",
    "delete position": null,
    "delete your account": null,
    "description": null,
    "design": null,
    "destroy group": null,
    "details": "dettagli",
    "did you mean:": null,
    "discard friend request": null,
    "discard user's request to join the group": null,
    "discussions": null,
    "display more": null,
    "distance from you": null,
    "distance:": "distanza:",
    "donate": "dona",
    "download": null,
    "download ebook": null,
    "ebooks": null,
    "edit": "modifica",
    "edit comment": "modifica commento",
    "edit data": "modifica dati",
    "edit data on Wikidata": null,
    "edit notes": "modifica note",
    "edit notifications": null,
    "Edit on Wikidata": null,
    "edit profile": "modifica profilo",
    "edit your position": null,
    "edited": null,
    "edition": null,
    "edition language": null,
    "edition subtitle": null,
    "edition title": null,
    "editions": "edizioni",
    "email": "email",
    "email address": null,
    "email me when": null,
    "email notifications settings": null,
    "email or password is incorrect": "email o passord non corrette",
    "email will not be publicly displayed.": null,
    "emails": null,
    "emails separated by a comma": "email separati da vi",
    "Empowering the Transition": "Migliora la transizione",
    "empty the queue": null,
    "enter an image url": null,
    "error": null,
    "ex:": null,
    "ex: the secret club of Proustian experts": null,
    "examples": null,
    "exchanges": null,
    "external scanner": null,
    "feedback": null,
    "filter": null,
    "filter group members": null,
    "filters": null,
    "find a group nearby": null,
    "find by ISBN": null,
    "find friends": "cerca amici",
    "find friends to share your inventory with!": null,
    "forgot password": "password dimenticata",
    "forgot password?": "password dimenticata?",
    "forgot your password?": null,
    "friend": null,
    "friend request sent": null,
    "friends": "amici",
    "friends & groups": null,
    "friends and groups": null,
    "friends requests": "richieste da amici",
    "from": null,
    "from a file": "da un file",
    "from a URL": "da un URL",
    "from:": null,
    "full-time team": null,
    "genre": null,
    "geolocation": null,
    "giving": null,
    "global": null,
    "go get it!": null,
    "go to the group inventory": null,
    "go to your inventory to see the imported books": null,
    "group": null,
    "group description can't be longer than 5000 characters": null,
    "group members": null,
    "group name": null,
    "group name can't be longer than 60 characters": null,
    "group URL:": null,
    "groups": "gruppi",
    "groups in common": null,
    "groups name can't be longer than 60 characters": null,
    "help": "help",
    "help other users to understand what this group is about": null,
    "help translate inventaire": null,
    "hide": "nascondi",
    "hide details": null,
    "history": null,
    "how to contribute": null,
    "I can lend it": "Posso prestarlo",
    "I have it and it's available for:": "C'è l'ho ed è disponibile per:",
    "I'm giving it": null,
    "I'm selling it": null,
    "import": null,
    "import a picture": null,
    "import this batch": null,
    "in my inventory": "nel mio inventario",
    "in your friends' and groups' inventories": null,
    "in your inventory": "nel tuo inventario",
    "interviews": null,
    "invalid description": null,
    "invalid email": "email non valida",
    "invalid ISBN": "ISBN non valido",
    "invalid property value": null,
    "invalid url": null,
    "invalid username": null,
    "inventaire id": null,
    "inventory": null,
    "inventorying": null,
    "invitation sent": null,
    "invitations": "inviti",
    "invite": null,
    "invite by email": null,
    "invite friends": null,
    "invite new members": null,
    "invited": null,
    "it doesn't look like an email": null,
    "Just Books. For now.": "Solo libri. Per il momento",
    "keep an inventory of your books": null,
    "labs": "laboratorio",
    "language": "lingua",
    "last 7 days": null,
    "last added": null,
    "last day": null,
    "learn more": null,
    "Learn more about Wikidata": null,
    "leave group": null,
    "lending": null,
    "loading": null,
    "login": "entra",
    "Login & connect your Wikidata account": null,
    "login to your inventory": null,
    "Look who was already there!": null,
    "make a one-time or recurrent donation": null,
    "make admin": null,
    "make an extended search": null,
    "make the inventory of your books and mutualize with your friends and communities into an infinite library!": null,
    "me": null,
    "means .\"inventory.\" in French": null,
    "member": null,
    "members": "membri",
    "members:": "membri:",
    "merge": null,
    "merge with another entity": null,
    "merge without importing data": null,
    "month": "mese",
    "more": "più",
    "more details": "più dettagli",
    "my inventory": null,
    "name": null,
    "nearby": "nelle vicinanze",
    "needed": null,
    "network": null,
    "new entity": null,
    "new password": null,
    "news": "notizie",
    "next": null,
    "next action": null,
    "no": "no",
    "no book selected": null,
    "no edition found": null,
    "no friends to invite": null,
    "no group found with this name": null,
    "no item found": null,
    "no item here": "nessun oggetto ",
    "no more pending requests": null,
    "no notification": "nessuna notifica",
    "no pending requests": null,
    "no request": "nessuna richiesta",
    "no result": null,
    "no suggestion found": null,
    "no user found": null,
    "non-monetary donations": null,
    "not found": null,
    "notifications": "notifiche",
    "ongoing": null,
    "only those who get the link or are invited can find this group": null,
    "oops": "oops",
    "or": "o",
    "or email address": null,
    "or login with": null,
    "ordinal": null,
    "other operations:": "altre operazioni:",
    "others": "altri",
    "otherwise": "altrimenti",
    "our love wasn't possible because": null,
    "our mission & values": null,
    "owner": "proprietario",
    "P1412": null,
    "P1476": "titolo originale",
    "P2635": null,
    "P364": "lingua originale",
    "P407": null,
    "P577": null,
    "P629": null,
    "pages": null,
    "partners": null,
    "password": "password",
    "password should be 8 characters minimum": "la password deve essere almeno di 8 caratteri",
    "pending": "in sospeso",
    "pending friends requests": "richieste di amicizia in sospeso",
    "personalized message": null,
    "photo credits:": null,
    "position": "posizione",
    "post comment": null,
    "precise the day and month": null,
    "precise the edition": null,
    "precise the year only": null,
    "previous searches": null,
    "private": "privato",
    "private notes": null,
    "profile": "profilo",
    "profile pic": "foto del profilo",
    "project": null,
    "public": "pubblico",
    "public books": null,
    "publisher": "pubblica",
    "read online": "leggi online",
    "received": null,
    "recent changes": null,
    "refresh data": null,
    "refresh Wikidata data": null,
    "refuse": null,
    "Remember the books you lend or borrow": null,
    "remove from group": null,
    "request to join the group": null,
    "request waiting for your answer": null,
    "request you sent": null,
    "requested": null,
    "requests": null,
    "requests waiting for your answer": null,
    "requests waiting your approval": null,
    "requests you sent": null,
    "requires an activated camera": null,
    "reset password": null,
    "retry": null,
    "return to the author's page": null,
    "return to the book's page": null,
    "return to the edition's page": null,
    "roadmap": null,
    "save": null,
    "save position": null,
    "scan": null,
    "scan a barcode": "scansiona un codice a barre",
    "search": "cerca",
    "search a book": "cerca un libro",
    "search a book by title, author or ISBN": "cerca un libro per titolo, autore o ISBN",
    "search a group": null,
    "search for users": null,
    "search for your friends": null,
    "Search possible duplicates": null,
    "Search your friends in the current users or invite them to join!": null,
    "see all": null,
    "see all editions": null,
    "see more": null,
    "see on the map": null,
    "see on Wikidata": null,
    "see profile": null,
    "see the API documentation": null,
    "select": "seleziona",
    "select a picture": null,
    "select an edition": null,
    "select the books you want to add": null,
    "select the group's position": null,
    "select the settings to apply to the selected books": null,
    "select this edition": null,
    "select your position": null,
    "selected": null,
    "selling": "vendendo",
    "send": "invia",
    "send an email to reset my password": null,
    "send email": null,
    "send feedback": null,
    "send friend request": null,
    "send invitations": null,
    "send request": null,
    "sent": null,
    "series": null,
    "set the group's position": null,
    "settings": "configurazioni",
    "share": "condividi",
    "share it with your friends and communities": "condividilo con i tuo amici e comunità",
    "show": "mostra",
    "show details": null,
    "sign out": "Disconnetti",
    "sign up": "iscriviti",
    "signal an error": null,
    "some of the last books listed": null,
    "something went wrong :(": null,
    "source": "sorgente",
    "subject": null,
    "Thank you for your message! Coming back to you shortly": null,
    "thanks!": "grazie!",
    "that would really help us if you could say a few words about why you're leaving:": null,
    "that's already your email": null,
    "that's already your username": null,
    "the bio can't be longer than 1000 characters": null,
    "The books you lend might actually come back now!": null,
    "The following data is missing on the Wikidata entity, which of those should be imported to Wikidata?": null,
    "the group has a position set": null,
    "the group's position isn't set yet": null,
    "the identifier near the book's barcode": null,
    "the issue was reported": null,
    "the library of your friends and communities": null,
    "this action can't be undone": null,
    "this book I can lend, this book I can give, this one is for sell...": null,
    "this edition is already in the list": null,
    "this email is already used": "inidirizzo email già in uso",
    "this email is unknown": null,
    "this group appears in search results": null,
    "this is visible by anyone who can see this item": null,
    "this ISBN already exist:": null,
    "this resource doesn't exist or you don't have the right to access it": null,
    "this resource requires to have admin rights to access it": null,
    "this username is already used": "nome utente già esistente",
    "this username isn't available": "questo username non è disponibile",
    "title": "titolo",
    "to:": null,
    "total contributions:": null,
    "totally randomly-selected messages from the people of the Internet": null,
    "transaction": null,
    "transactions": null,
    "translate": null,
    "translation": null,
    "type": null,
    "unavailable": null,
    "unfriend": "togli amicizia",
    "unknown": null,
    "unselect": null,
    "update password": null,
    "upload your collection from another website": null,
    "url": "url",
    "use the barcode scanner": null,
    "user": null,
    "user search": null,
    "username": "nome utente",
    "username can only contain letters, figures or _": null,
    "username can't contain space": "il nome utente non può contenere spazi",
    "username or password is incorrect": "nome utente o password non corretti",
    "username or password is invalid": null,
    "username should be 2 characters minimum": null,
    "username should be 20 characters maximum": "il nome utente può contenere massimo 20 caratteri",
    "users": null,
    "validate": "valida",
    "validate and add another book": null,
    "validate user's request to join the group": null,
    "via the API": null,
    "videos": null,
    "visibility": null,
    "waiting for your answer": null,
    "Welcome": "Benvenuto",
    "welcome in your inventory!": null,
    "Welcome on Inventaire": "Benvenuto su Inventaire",
    "welcome screen": null,
    "which edition?": null,
    "while you're there,": null,
    "Who can see it?": "Chi lo può vedere?",
    "wiki": "wiki",
    "wikidata entities can't link to inventaire entities": null,
    "work": null,
    "works": null,
    "wrong password": null,
    "wrong user": null,
    "year": "anno",
    "yes": "si",
    "you are offline": null,
    "you aren't connected to anyone yet": null,
    "you aren't in any group yet": null,
    "you can now find books people nearby have to give, share or sell!": null,
    "you can't leave the group without naming another admin": null,
    "you have a position set": null,
    "you have no more pending invitations": null,
    "you need to be connected to add a book to your inventory": null,
    "you need to be connected to comment": null,
    "you need to be connected to edit this page": null,
    "you need to be connected to send a friend request": null,
    "You own your data": "I tuoi dati ti appartengono",
    "you requested to join is waiting for approval": null,
    "you?": null,
    "your friends": "i tuoi amici",
    "your friends and communities are the best library": null,
    "your friends and communities are your best library": null,
    "your groups": null,
    "your message": null,
    "your position isn't set yet": null
}